websight/__init__.py
websight/agent/__init__.py
websight/agent/agent.py
websight/agent/browser.py
websight/model/actions.py
websight/model/llm.py
websight/model/prompts.py
websight/model/websight.py
websight-0.1.2.dist-info/METADATA
websight-0.1.2.dist-info/WHEEL
websight-0.1.2.dist-info/top_level.txt
websight-0.1.2.dist-info/RECORD
