Metadata-Version: 2.4
Name: websight
Version: 0.1.2
Summary: A Vision-First Architecture for Robust Web Agents
Requires-Python: >=3.12
Requires-Dist: colorama>=0.4.6
Requires-Dist: datasets>=3.6.0
Requires-Dist: httpx>=0.28.1
Requires-Dist: huggingface-hub>=0.30.2
Requires-Dist: matplotlib>=3.10.1
Requires-Dist: openai>=1.82.0
Requires-Dist: peft>=0.15.2
Requires-Dist: pillow>=11.2.1
Requires-Dist: playwright>=1.52.0
Requires-Dist: pydantic>=2.10.5
Requires-Dist: python-dotenv>=1.1.0
Requires-Dist: pyyaml>=6.0.2
Requires-Dist: rich>=14.0.0
Requires-Dist: torchvision>=0.22.0
Requires-Dist: tqdm>=4.67.1
Requires-Dist: transformers>=4.52.4
Requires-Dist: webdriver-manager>=4.0.2
